[{"annotation_class": "HOLE", "annotation_type": "box", "annotation_value": {"x": 492.520402392884, "y": 573.7901359208656, "width": 18.299070332722238, "height": 19.479682317951188}}, {"annotation_class": "CHIPSET", "annotation_type": "box", "annotation_value": {"x": 376.17874508953645, "y": 430.00322548458934, "width": 66.80101104832926, "height": 64.9955751211811}}, {"annotation_class": "BOOTSEL", "annotation_type": "box", "annotation_value": {"x": 405.0657041527004, "y": 532.912923398675, "width": 36.10864717512089, "height": 41.524932597367524}}, {"annotation_class": "HOLE", "annotation_type": "box", "annotation_value": {"x": 366.7880005271634, "y": 314.0612785389633, "width": 22.431147527706514, "height": 21.250556387432425}}, {"annotation_class": "USB", "annotation_type": "box", "annotation_value": {"x": 438.421052631579, "y": 564.3972835314091, "width": 75.1103565365026, "height": 70.35653650254665}}, {"annotation_class": "HOLE", "annotation_type": "box", "annotation_value": {"x": 428.76875312997186, "y": 603.3047788051728, "width": 19.479638082276068, "height": 18.299069581116214}}, {"annotation_class": "OSCILLATOR", "annotation_type": "box", "annotation_value": {"x": 353.4203743513858, "y": 410.58913862906604, "width": 35.18078888823402, "height": 28.01435279659796}}, {"annotation_class": "RASPBERRY PICO", "annotation_type": "box", "annotation_value": {"x": 277.74193548387103, "y": 298.1833616298811, "width": 263.36162988115456, "height": 344.17657045840406}}, {"annotation_class": "HOLE", "annotation_type": "box", "annotation_value": {"x": 303.626680174801, "y": 344.1662277916878, "width": 21.250534742379784, "height": 20.660250019014995}}]